rtichoke/__init__.py
rtichoke/calibration/__init__.py
rtichoke/calibration/calibration.py
rtichoke/discrimination/__init__.py
rtichoke/discrimination/gains.py
rtichoke/discrimination/lift.py
rtichoke/discrimination/precision_recall.py
rtichoke/discrimination/roc.py
rtichoke/performance_data/__init__.py
rtichoke/performance_data/performance_data.py
rtichoke/performance_data/performance_data_times.py
rtichoke/processing/__init__.py
rtichoke/processing/adjustments.py
rtichoke/processing/combinations.py
rtichoke/processing/exported_functions.py
rtichoke/processing/plotly_helper_functions.py
rtichoke/processing/send_post_request_to_r_rtichoke.py
rtichoke/processing/transforms.py
rtichoke/rtichoke.py
rtichoke/summary_report/__init__.py
rtichoke/summary_report/summary_report.py
rtichoke/summary_report/summary_report_template.qmd
rtichoke/summary_report/summary_report_template_files/libs/bootstrap/bootstrap-icons.woff
rtichoke/utility/__init__.py
rtichoke/utility/decision.py
rtichoke-0.1.28.dist-info/WHEEL
rtichoke-0.1.28.dist-info/METADATA
rtichoke-0.1.28.dist-info/RECORD
