Metadata-Version: 2.3
Name: rtichoke
Version: 0.1.28
Summary: interactive visualizations for performance of predictive models
Author: Uriah Finkel
License: MIT
Requires-Dist: plotly>=5.13.1,<6.0.0
Requires-Dist: pandas>=2.2.3
Requires-Dist: typing>=3.7.4.3
Requires-Dist: polarstate==0.1.8
Requires-Dist: marimo>=0.17.0
Requires-Dist: pyarrow>=21.0.0
Requires-Dist: statsmodels>=0.14.0
Requires-Dist: polars>=1.31.0
Requires-Python: >=3.9
